CHANGELOG.txt
LICENCE.txt
MANIFEST.in
README.txt
setup.py
FuzzyMath/__init__.py
Fuzzy_Math.egg-info/PKG-INFO
Fuzzy_Math.egg-info/SOURCES.txt
Fuzzy_Math.egg-info/dependency_links.txt
Fuzzy_Math.egg-info/top_level.txt