Metadata-Version: 1.1
Name: Fuzzy-Math
Version: 0.0.1
Summary: Performs Fuzzy Math Functions
Home-page: UNKNOWN
Author: Nicholas R Furth
Author-email: nf77@njit.edu
License: MIT
Keywords: Fuzzy Math
Platform: UNKNOWN
Classifier: Development Status :: 5 - Production/Stable
Classifier: Intended Audience :: Education
Classifier: Operating System :: Microsoft :: Windows :: Windows 10
Classifier: License :: OSI Approved :: MIT License
Classifier: Programming Language :: Python :: 3
